<?xml version="1.0"?>

<?xml-stylesheet type="text/xsl" href="config_definition.xsl" ?>

<config_definition>

<entry id="cism_bld" >
</entry>
<entry id="cism_root" >
</entry>
<entry id="cppdefs" >
</entry>
<entry id="spmd" valid_values="0,1" value="1">
</entry>
<entry id="command_line" valid_values="0,1" value="0">
</entry>
<entry id="coupled" valid_values="0,1" value="1">
</entry>
<entry id="profiling" valid_values="0,1" value="0">
If want to profile the cpu time in the code (1=on, 0=off)
</entry>
<entry id="no_vertical_diffusion" valid_values="0,1" value="0">
Turn vertical diffusion off (1=on, 0=off)
</entry>
<entry id="no_horizontal_advection" valid_values="0,1" value="0">
Turn horizontal advection  off (1=on, 0=off)
</entry>
<entry id="no_vertical_advection" valid_values="0,1" value="0">
Turn horizontal advection  off (1=on, 0=off)
</entry>
<entry id="no_strain_heat" valid_values="0,1" value="0">
Turn strain heating off (1=on, 0=off)
</entry>
<entry id="debug_picard" valid_values="0,1" value="0">
Turn debugging print statements for the Picard iterations on (1=on, 0=off)
</entry>
<entry id="debug_coords" valid_values="0,1" value="0">
Turn debugging print statements for coordinates on (1=on, 0=off)
</entry>
<entry id="glimmer_sp" valid_values="1,2" value="1">
Turn single precision on (1=single,2=double)
</entry>
<entry id="debug_print" valid_values="0,1" value="0">
Turn general debugging print statements on (1=on, 0=off)
</entry>
<entry id="debug_rebound" valid_values="0,1" value="0">
Turn debug writing out elastic rebound state to file on (1=on, 0=off)
</entry>
<entry id="use_enmabal" valid_values="0,1" value="0">
Turn use of energy mass balance scheme on rather than calculating in clm (1=on, 0=off)
</entry>
<entry id="have_avg" valid_values="0,1" value="0">
If should write out averages to output files
</entry>
<entry id="have_config_h" valid_values="0,1" value="0">
If have a config.inc file to use
</entry>
<entry id="restarts" valid_values="0,1" value="1">
If enabling writing out restart information out
</entry>
<entry id="comp_interface" valid_values="ESMF,MCT,cpl_\$COMP" value="MCT">
Component framework interface to use (MCT, ESMF or cpl_${COMP})
</entry>
<entry id="usr_src" value="" list="1">
User source directories to prepend to the filepath.  Multiple directories
are specified as a comma separated list with no embedded white space.
</entry>
<entry id="debug" valid_values="0,1" value="0">
Switch to enable debugging options for Fortran compiler: 0=off, 1=on.
</entry>
<entry id="mach" value="bluefire">
CCSM build machine name and compiler
</entry>
<entry id="target_os" value="">
OS for which CISM is being built.  The value is the name returned by the "uname -s"
command on the target platform.  This parameter is to allow cross-compilation.
</entry>

</config_definition>
